votingai/__init__.py
votingai/config.py
votingai/py.typed
votingai/security.py
votingai/voting_group_chat.py
votingai-1.0.2.dist-info/licenses/LICENSE
votingai-1.0.2.dist-info/METADATA
votingai-1.0.2.dist-info/WHEEL
votingai-1.0.2.dist-info/top_level.txt
votingai-1.0.2.dist-info/RECORD
