Metadata-Version: 2.4
Name: votingai
Version: 1.0.2
Summary: VotingAI: Democratic Multi-Agent Systems Built on AutoGen
Author-email: Tejas Dharani <tejas.dharani10@gmail.com>
Maintainer-email: Tejas Dharani <tejas.dharani10@gmail.com>
License: MIT
Project-URL: Homepage, https://github.com/tejas-dharani/votingai
Project-URL: Repository, https://github.com/tejas-dharani/votingai.git
Project-URL: Issues, https://github.com/tejas-dharani/votingai/issues
Project-URL: Changelog, https://github.com/tejas-dharani/votingai/blob/main/CHANGELOG.md
Keywords: votingai,voting,multi-agent,consensus,ai,agents,democracy,autogen
Classifier: Development Status :: 4 - Beta
Classifier: Intended Audience :: Developers
Classifier: License :: OSI Approved :: MIT License
Classifier: Programming Language :: Python :: 3
Classifier: Programming Language :: Python :: 3.10
Classifier: Programming Language :: Python :: 3.11
Classifier: Programming Language :: Python :: 3.12
Classifier: Topic :: Scientific/Engineering :: Artificial Intelligence
Classifier: Topic :: Software Development :: Libraries :: Python Modules
Classifier: Topic :: Communications
Classifier: Framework :: AsyncIO
Requires-Python: >=3.10
License-File: LICENSE
Requires-Dist: autogen-agentchat>=0.4.0
Requires-Dist: autogen-core>=0.4.0
Requires-Dist: autogen-ext[openai]>=0.4.0
Requires-Dist: matplotlib>=3.10.5
Requires-Dist: numpy>=2.2.6
Requires-Dist: openai>=1.99.0
Requires-Dist: pandas>=2.3.1
Requires-Dist: seaborn>=0.13.2
Provides-Extra: dev
Requires-Dist: pytest>=7.0; extra == "dev"
Requires-Dist: pytest-asyncio>=0.21.0; extra == "dev"
Requires-Dist: pytest-cov>=4.0; extra == "dev"
Requires-Dist: pytest-xdist>=3.0; extra == "dev"
Requires-Dist: ruff>=0.1.0; extra == "dev"
Requires-Dist: pyright>=1.1.0; extra == "dev"
Requires-Dist: mypy>=1.0; extra == "dev"
Requires-Dist: bandit[toml]>=1.7.0; extra == "dev"
Requires-Dist: poethepoet>=0.20.0; extra == "dev"
Provides-Extra: docs
Requires-Dist: sphinx>=6.0; extra == "docs"
Requires-Dist: sphinx-rtd-theme>=1.2.0; extra == "docs"
Requires-Dist: myst-parser>=0.18.0; extra == "docs"
Dynamic: license-file
